ponderosa/__init__.py
ponderosa/ponderosa.py
ponderosa-0.5.1.dist-info/LICENSE
ponderosa-0.5.1.dist-info/METADATA
ponderosa-0.5.1.dist-info/WHEEL
ponderosa-0.5.1.dist-info/RECORD
