Metadata-Version: 2.1
Name: ponderosa
Version: 0.5.1
Summary: 
Home-page: https://github.com/camillescott/ponderosa
License: BSD-3-Clause
Author: Camille Scott
Author-email: camille@bogg.cc
Requires-Python: >=3.12,<4.0
Classifier: License :: OSI Approved :: BSD License
Classifier: Operating System :: MacOS :: MacOS X
Classifier: Operating System :: Microsoft :: Windows
Classifier: Operating System :: POSIX :: Linux
Classifier: Programming Language :: Python :: 3
Classifier: Programming Language :: Python :: 3.12
Classifier: Programming Language :: Python :: 3.13
Classifier: Topic :: Software Development :: Libraries
Classifier: Topic :: Software Development :: User Interfaces
Classifier: Topic :: Utilities
Provides-Extra: rich
Requires-Dist: rich (>=13.9.4,<14.0.0) ; extra == "rich"
